keepvariable/__init__.py
keepvariable/keepvariable_core.py
keepvariable/keepvariable_model.py
keepvariable/kv_redis_example.py
keepvariable/utils.py
keepvariable-1.2.14.dist-info/LICENSE
keepvariable-1.2.14.dist-info/METADATA
keepvariable-1.2.14.dist-info/WHEEL
keepvariable-1.2.14.dist-info/top_level.txt
keepvariable-1.2.14.dist-info/RECORD
