Metadata-Version: 2.1
Name: keepvariable
Version: 1.2.14
Summary: A Python package keeping the values of variables between separate runs in a seamless and effortless way.
Home-page: https://github.com/DovaX/keepvariable
Author: DovaX
Author-email: dovax.ai@gmail.com
Classifier: Programming Language :: Python :: 3
Classifier: License :: OSI Approved :: MIT License
Classifier: Operating System :: OS Independent
Requires-Python: >=3.6
License-File: LICENSE
Requires-Dist: redis
